Workbook
Name Categoria: 'Strutture ricettive'!$A$2:$A$1048576
Name Città: 'Strutture ricettive'!$E$2:$E$1048576
Name Denominazione: 'Strutture ricettive'!$B$2:$B$1048576
Name Indirizzo: 'Strutture ricettive'!$D$2:$D$1048576
Name Indirizzo_di_posta_elettronica: 'Strutture ricettive'!$I$2:$I$1048576
Name Indirizzo_internet: 'Strutture ricettive'!$H$2:$H$1048576
Name Localita: 'Strutture ricettive'!$G$2:$G$1048576
Name Nome_Struttura: '[1]Strutture ricettive'!$B$2:$B$1048576

Sheet Strutture ricettive
A1: Categoria | B1: Denominazione | C1: Annulla spazi | D1: Indirizzo | E1: Città | F1: Chiave | G1: Localita | H1: Indirizzo internet | I1: Indirizzo di posta elettronica
A2: ALLOGGI IN AFFITTO | B2: 124 AFFITTACAMERE | C2: =TRIM(B2) -> 124 AFFITTACAMERE | D2: via Sandro Pertini 55 | E2: TOLENTINO | F2: =C2&"_"&E2&"_"&D2 -> 124 AFFITTACAMERE_TOLENTINO_via Sandro Pertini 55 | I2: info@124tolentino.it.
A3: ALLOGGI IN AFFITTO | B3: 2000 di DIAMANTINI ASSUNTA | C3: =TRIM(B3) -> 2000 di DIAMANTINI ASSUNTA | D3: via giacomo puccini 9 | E3: SASSOCORVARO | F3: =C3&"_"&E3&"_"&D3 -> 2000 di DIAMANTINI ASSUNTA_SASSOCORVARO_via giacomo puccini 9 | G3: SASSOCORVARO | I3: fabbrica-delle-idee@libero.it
A4: ALLOGGI IN AFFITTO | B4: 3 JOLIE | C4: =TRIM(B4) -> 3 JOLIE | D4: viale Caduti del Lavoro 1 | E4: SIROLO | F4: =C4&"_"&E4&"_"&D4 -> 3 JOLIE_SIROLO_viale Caduti del Lavoro 1 | G4: SIROLO | H4: www.cameresirolo.com | I4: info@cameresirolo.com
A5: STABILIMENTI BALNEARI | B5: 30 NODI | C5: =TRIM(B5) -> 30 NODI | D5: via del golfo 25 | E5: NUMANA | F5: =C5&"_"&E5&"_"&D5 -> 30 NODI_NUMANA_via del golfo 25 | G5: NUMANA | I5: alexpanocchi@hotmail.com
A6: BED & BREAKFAST | B6: 4 PINI | C6: =TRIM(B6) -> 4 PINI | D6: Via della Madonnetta 10/A | E6: ANCONA | F6: =C6&"_"&E6&"_"&D6 -> 4 PINI_ANCONA_Via della Madonnetta 10/A | G6: ANCONA | H6: http://www.4pini.it | I6: info@4pini.it
A7: STABILIMENTI BALNEARI | B7: 4 SORELLE | C7: =TRIM(B7) -> 4 SORELLE | D7: viale alcide de gasperi 1 1 | E7: GROTTAMMARE | F7: =C7&"_"&E7&"_"&D7 -> 4 SORELLE_GROTTAMMARE_viale alcide de gasperi 1 1
A8: CAMPEGGI | B8: 4 STAGIONI | C8: =TRIM(B8) -> 4 STAGIONI | D8: contrada Brilli 1 | E8: SARNANO | F8: =C8&"_"&E8&"_"&D8 -> 4 STAGIONI_SARNANO_contrada Brilli 1 | G8: SARNANO | H8: www.camping4stagioni.it | I8: quattrostagioni@camping.it
A9: STABILIMENTI BALNEARI | B9: 45.COM | C9: =TRIM(B9) -> 45.COM | E9: SAN BENEDETTO DEL TRONTO | F9: =C9&"_"&E9&"_"&D9 -> 45.COM_SAN BENEDETTO DEL TRONTO_
A10: ALTRI ALLOGGI PRIVATI | B10: 5 ALBERI | C10: =TRIM(B10) -> 5 ALBERI | D10: via Gualdo 7 | E10: BELVEDERE OSTRENSE | F10: =C10&"_"&E10&"_"&D10 -> 5 ALBERI_BELVEDERE OSTRENSE_via Gualdo 7 | H10: www.5alberi.com | I10: info@5alberi.com
A11: BED & BREAKFAST | B11: 5 COLLI | C11: =TRIM(B11) -> 5 COLLI | D11: COLLE SANT'ANGELO 32A | E11: MONTEPRANDONE | F11: =C11&"_"&E11&"_"&D11 -> 5 COLLI_MONTEPRANDONE_COLLE SANT'ANGELO 32A | H11: cinquecolli.bnb@hotmail.com | I11: bruni.cinzia@hotmail.it
A12: TURISMO RURALE | B12: 9 CAMERE | C12: =TRIM(B12) -> 9 CAMERE | D12: via Cave 5 | E12: SIROLO | F12: =C12&"_"&E12&"_"&D12 -> 9 CAMERE_SIROLO_via Cave 5 | H12: www.novecamere.it | I12: info@novecamere.it
A13: ALLOGGI AGRITURISTICI | B13: A 3 PASSI | C13: =TRIM(B13) -> A 3 PASSI | D13: via del Carmine 51 | E13: ANCONA | F13: =C13&"_"&E13&"_"&D13 -> A 3 PASSI_ANCONA_via del Carmine 51 | H13: www.a3passi.com | I13: a3passi@aziendadelcarmine.it
A14: ALLOGGI AGRITURISTICI | B14: A CASA DA ANGELO | C14: =TRIM(B14) -> A CASA DA ANGELO | D14: contrada San Giacomo 26 | E14: GROTTAMMARE | F14: =C14&"_"&E14&"_"&D14 -> A CASA DA ANGELO_GROTTAMMARE_contrada San Giacomo 26 | G14: GROTTAMMARE | I14: agriturismoacasadaangelo@alice.it
A15: BED & BREAKFAST | B15: A CASA DI NONNA DI CROIA MAURO | C15: =TRIM(B15) -> A CASA DI NONNA DI CROIA MAURO | D15: VIA ABRUZZO 7 | E15: LORETO | F15: =C15&"_"&E15&"_"&D15 -> A CASA DI NONNA DI CROIA MAURO_LORETO_VIA ABRUZZO 7 | G15: LORETO | I15: maurocroia@alice.it
A16: BED & BREAKFAST | B16: A CASA DI NONNA LINDA | C16: =TRIM(B16) -> A CASA DI NONNA LINDA | D16: Via Gherardi 54 | E16: SENIGALLIA | F16: =C16&"_"&E16&"_"&D16 -> A CASA DI NONNA LINDA_SENIGALLIA_Via Gherardi 54 | G16: SENIGALLIA | I16: info@acasadinonnalinda.it
A17: BED & BREAKFAST | B17: A CASA DI PAOLA | C17: =TRIM(B17) -> A CASA DI PAOLA | D17: viale Giovanni XXIII 6 | E17: JESI | F17: =C17&"_"&E17&"_"&D17 -> A CASA DI PAOLA_JESI_viale Giovanni XXIII 6 | H17: www.casapaola.it | I17: info@casapaola.it
A18: BED & BREAKFAST | B18: A CASA DI PETER | C18: =TRIM(B18) -> A CASA DI PETER | D18: VIA O.MARCHETTI 24 | E18: CIVITANOVA MARCHE | F18: =C18&"_"&E18&"_"&D18 -> A CASA DI PETER_CIVITANOVA MARCHE_VIA O.MARCHETTI 24 | G18: CIVITANOVA MARCHE | I18: pietro.forani@virgilio.it
A19: BED & BREAKFAST | B19: A CASA DI ROMOLO | C19: =TRIM(B19) -> A CASA DI ROMOLO | D19: via Ramazzani 144 | E19: ARCEVIA | F19: =C19&"_"&E19&"_"&D19 -> A CASA DI ROMOLO_ARCEVIA_via Ramazzani 144 | G19: ARCEVIA | I19: acasadiromolo@gmail.com
A20: BED & BREAKFAST | B20: A DUE PASSI DAL CIELO | C20: =TRIM(B20) -> A DUE PASSI DAL CIELO | D20: VIALE DELLA VITTORIA 72 | E20: JESI | F20: =C20&"_"&E20&"_"&D20 -> A DUE PASSI DAL CIELO_JESI_VIALE DELLA VITTORIA 72 | G20: JESI | I20: aduepassidalcielo@tim.it
A21: STABILIMENTI BALNEARI | B21: ABBADETTA MARE | C21: =TRIM(B21) -> ABBADETTA MARE | D21: lungomare marconi 5 5 | E21: SAN BENEDETTO DEL TRONTO | F21: =C21&"_"&E21&"_"&D21 -> ABBADETTA MARE_SAN BENEDETTO DEL TRONTO_lungomare marconi 5 5 | G21: SENIGALLIA | H21: info@lapacehotel.it | I21: www.lapacehotel.it
A22: ALBERGHI | B22: ABBADETTA RESORT | C22: =TRIM(B22) -> ABBADETTA RESORT | D22: via Abbadetta 36 | E22: ACQUAVIVA PICENA | F22: =C22&"_"&E22&"_"&D22 -> ABBADETTA RESORT_ACQUAVIVA PICENA_via Abbadetta 36 | G22: ACQUAVIVA PICENA | H22: www.abbadetta.it | I22: sabrina-riccioni@hotmail.com
A23: CASE PER FERIE | B23: ABBADIA DI ELCITO | C23: =TRIM(B23) -> ABBADIA DI ELCITO | D23: localita' Elcito 1 | E23: SAN SEVERINO MARCHE | F23: =C23&"_"&E23&"_"&D23 -> ABBADIA DI ELCITO_SAN SEVERINO MARCHE_localita' Elcito 1 | G23: SAN SEVERINO MARCHE | I23: edo11@libero.it
A24: ALBERGHI | B24: ABBAZIA CLUB HOTEL | C24: =TRIM(B24) -> ABBAZIA CLUB HOTEL | D24: viale Cristoforo Colombo 107 | E24: MONDOLFO | F24: =C24&"_"&E24&"_"&D24 -> ABBAZIA CLUB HOTEL_MONDOLFO_viale Cristoforo Colombo 107 | G24: MONDOLFO | H24: www.clubhotel-marotta.com | I24: info@clubhotel-marotta.com
A25: OSTELLI PER LA GIOVENTU' | B25: ABBAZIA DI SAN BIAGIO IL CAPRILE | C25: =TRIM(B25) -> ABBAZIA DI SAN BIAGIO IL CAPRILE | D25: frazione Campodonico 91/b | E25: FABRIANO | F25: =C25&"_"&E25&"_"&D25 -> ABBAZIA DI SAN BIAGIO IL CAPRILE_FABRIANO_frazione Campodonico 91/b | G25: FABRIANO | H25: www.sanbiagioincaprile.it | I25: hostellosanbiagio@libero.it
A26: STABILIMENTI BALNEARI | B26: ABBRONZATISSIMA | C26: =TRIM(B26) -> ABBRONZATISSIMA | D26: via cristoforo colombo 1 1 | E26: FALCONARA MARITTIMA | F26: =C26&"_"&E26&"_"&D26 -> ABBRONZATISSIMA_FALCONARA MARITTIMA_via cristoforo colombo 1 1 | G26: FALCONARA MARITTIMA
A27: ALLOGGI IN AFFITTO | B27: ABRAMO | C27: =TRIM(B27) -> ABRAMO | D27: via annibal caro 80 | E27: PORTO RECANATI | F27: =C27&"_"&E27&"_"&D27 -> ABRAMO_PORTO RECANATI_via annibal caro 80 | G27: PORTO RECANATI | H27: www.abramocamere.it | I27: info@abramocamere.it
A28: TURISMO RURALE | B28: ACANTO COUNTRY HOUSE | C28: =TRIM(B28) -> ACANTO COUNTRY HOUSE | D28: via Ancarano 18 | E28: SIROLO | F28: =C28&"_"&E28&"_"&D28 -> ACANTO COUNTRY HOUSE_SIROLO_via Ancarano 18 | G28: SIROLO | H28: www.acantocountryhouse.com | I28: info@acantocountryhouse.com
A29: STABILIMENTI BALNEARI | B29: ACAPULCO | C29: =TRIM(B29) -> ACAPULCO | E29: PORTO RECANATI | F29: =C29&"_"&E29&"_"&D29 -> ACAPULCO_PORTO RECANATI_ | G29: PORTO RECANATI
A30: ALLOGGI AGRITURISTICI | B30: ACCIPICCHIA | C30: =TRIM(B30) -> ACCIPICCHIA | D30: contrada campana 146 | E30: ANCONA | F30: =C30&"_"&E30&"_"&D30 -> ACCIPICCHIA_ANCONA_contrada campana 146 | G30: collina di PORTONOVO | H30: www.cantinapolenta.it | I30: info@cantinapolenta.it
A31: ALLOGGI IN AFFITTO | B31: ACCOMODATION CASA CAVOUR | C31: =TRIM(B31) -> ACCOMODATION CASA CAVOUR | D31: G.MORETTI 1 | E31: SAN BENEDETTO DEL TRONTO | F31: =C31&"_"&E31&"_"&D31 -> ACCOMODATION CASA CAVOUR_SAN BENEDETTO DEL TRONTO_G.MORETTI 1 | H31: www.casacavoursanbenedetto.it | I31: info@casacavoursanbenedetto.it
A32: ALTRI ALLOGGI PRIVATI | B32: ACERO FRANCESCO E FILIPPO | C32: =TRIM(B32) -> ACERO FRANCESCO E FILIPPO | D32: via Monte Polo 10 | E32: URBINO | F32: =C32&"_"&E32&"_"&D32 -> ACERO FRANCESCO E FILIPPO_URBINO_via Monte Polo 10 | I32: m.g.acero@alice.it
A33: ALTRI ALLOGGI PRIVATI | B33: ACERO MARIA GRAZIA | C33: =TRIM(B33) -> ACERO MARIA GRAZIA | D33: via Monte Polo 8 | E33: URBINO | F33: =C33&"_"&E33&"_"&D33 -> ACERO MARIA GRAZIA_URBINO_via Monte Polo 8 | I33: m.g.acero@alice.it
A34: ALLOGGI AGRITURISTICI | B34: ACQUABATTIGLIA | C34: =TRIM(B34) -> ACQUABATTIGLIA | D34: via fossato 5 | E34: CANTIANO | F34: =C34&"_"&E34&"_"&D34 -> ACQUABATTIGLIA_CANTIANO_via fossato 5 | G34: ACQUABATTAGLIA | H34: www.acquabattaglia.com | I34: picorri@gmail.com
A35: ALLOGGI IN AFFITTO | B35: ACQUAMARINA | C35: =TRIM(B35) -> ACQUAMARINA | D35: via C. Maffei 68 | E35: SAN BENEDETTO DEL TRONTO | F35: =C35&"_"&E35&"_"&D35 -> ACQUAMARINA_SAN BENEDETTO DEL TRONTO_via C. Maffei 68 | H35: www.residenceacquamarina.com | I35: info@appartamentiacquamarina.it
A36: TURISMO RURALE | B36: ACQUANERA | C36: =TRIM(B36) -> ACQUANERA | D36: localita' acquanera 1 | E36: PIOBBICO | F36: =C36&"_"&E36&"_"&D36 -> ACQUANERA_PIOBBICO_localita' acquanera 1 | G36: PIOBBICO | H36: www.acquanera.com | I36: info@acquanera.com
A37: ALBERGHI | B37: ACQUAPARCO VERDE AZZURRO | C37: =TRIM(B37) -> ACQUAPARCO VERDE AZZURRO | D37: localita' San Faustino 6 | E37: CINGOLI | F37: =C37&"_"&E37&"_"&D37 -> ACQUAPARCO VERDE AZZURRO_CINGOLI_localita' San Faustino 6 | G37: CINGOLI | H37: www.verdeazzurro.it | I37: info@verdeazzurro.it
A38: ALLOGGI IN AFFITTO | B38: ACQUAPAZZA ROOM | C38: =TRIM(B38) -> ACQUAPAZZA ROOM | D38: via San Martino 58 | E38: SAN BENEDETTO DEL TRONTO | F38: =C38&"_"&E38&"_"&D38 -> ACQUAPAZZA ROOM_SAN BENEDETTO DEL TRONTO_via San Martino 58 | I38: info@acquapazzaristorante.it
A39: STABILIMENTI BALNEARI | B39: ACQUARIUS | C39: =TRIM(B39) -> ACQUARIUS | D39: viale alcide de gasperi 1 1 | E39: GROTTAMMARE | F39: =C39&"_"&E39&"_"&D39 -> ACQUARIUS_GROTTAMMARE_viale alcide de gasperi 1 1 | G39: GROTTAMMARE
A40: ALLOGGI AGRITURISTICI | B40: ACQUASALATA | C40: =TRIM(B40) -> ACQUASALATA | D40: fraz. Montale 116 | E40: ARCEVIA | F40: =C40&"_"&E40&"_"&D40 -> ACQUASALATA_ARCEVIA_fraz. Montale 116 | G40: MONTALE | H40: www.agriturismoacquasalata.it | I40: a.acquasalata@libero.it
A41: TURISMO RURALE | B41: ACQUAVIVA di CECCHI PEPPINO | C41: =TRIM(B41) -> ACQUAVIVA di CECCHI PEPPINO | D41: contrada acquaviva san paterniano 34 | E41: LORO PICENO | F41: =C41&"_"&E41&"_"&D41 -> ACQUAVIVA di CECCHI PEPPINO_LORO PICENO_contrada acquaviva san paterniano 34 | G41: LORO PICENO | H41: www.countryhouseacquaviva.it | I41: p.cecchi@tiscali.it
A42: STABILIMENTI BALNEARI | B42: ACROPOLI | C42: =TRIM(B42) -> ACROPOLI | E42: PORTO RECANATI | F42: =C42&"_"&E42&"_"&D42 -> ACROPOLI_PORTO RECANATI_ | G42: PORTO RECANATI | H42: mmonina@tiscali.it | I42: www.acropoli-mb.it
A43: ALBERGHI | B43: ACRUX | C43: =TRIM(B43) -> ACRUX | D43: via Vittorio Veneto 146 | E43: GABICCE MARE | F43: =C43&"_"&E43&"_"&D43 -> ACRUX_GABICCE MARE_via Vittorio Veneto 146 | G43: GABICCE MARE | H43: www.hotelacrux.com | I43: info@hotelacrux.com
A44: RESIDENZE TURISTICO ALBERGHIERE | B44: ADA | C44: =TRIM(B44) -> ADA | D44: lungomare alcide de gasperi 76 | E44: GROTTAMMARE | F44: =C44&"_"&E44&"_"&D44 -> ADA_GROTTAMMARE_lungomare alcide de gasperi 76 | G44: GROTTAMMARE | H44: www.residenceada.com | I44: info@residenceada.com
A45: ALLOGGI IN AFFITTO | B45: ADAMO ED EVA RESORT | C45: =TRIM(B45) -> ADAMO ED EVA RESORT | D45: via Costa Verde snc | E45: NUMANA | F45: =C45&"_"&E45&"_"&D45 -> ADAMO ED EVA RESORT_NUMANA_via Costa Verde snc | G45: Marcelli | H45: www.adamoedevanumana.it | I45: info@adamoedevanumana.it
A46: ALBERGHI | B46: ADLER | C46: =TRIM(B46) -> ADLER | D46: viale mare 13 | E46: GABICCE MARE | F46: =C46&"_"&E46&"_"&D46 -> ADLER_GABICCE MARE_viale mare 13 | G46: GABICCE MARE | H46: www.adlerhotel.eu | I46: info@adlerhotel.eu
A47: ALBERGHI | B47: ADRIA | C47: =TRIM(B47) -> ADRIA | D47: Via Vittorio Veneto 25 | E47: GABICCE MARE | F47: =C47&"_"&E47&"_"&D47 -> ADRIA_GABICCE MARE_Via Vittorio Veneto 25 | G47: GABICCE MARE | H47: www.hoteladriagabicce.it | I47: info@hoteladriagabicce.it
A48: ALTRI ALLOGGI PRIVATI | B48: ADRIAN ARTHUR THOMAS GARDNER | C48: =TRIM(B48) -> ADRIAN ARTHUR THOMAS GARDNER | D48: C.DA REGNANO SNC | E48: TOLENTINO | F48: =C48&"_"&E48&"_"&D48 -> ADRIAN ARTHUR THOMAS GARDNER_TOLENTINO_C.DA REGNANO SNC | G48: TOLENTINO
A49: ALLOGGI IN AFFITTO | B49: ADRIATICA | C49: =TRIM(B49) -> ADRIATICA | D49: via del Porto 42 | E49: NUMANA | F49: =C49&"_"&E49&"_"&D49 -> ADRIATICA_NUMANA_via del Porto 42 | G49: NUMANA | H49: www.affitticonero.com | I49: immobiliareadriatica@tiscali.it
A50: RESIDENZE TURISTICO ALBERGHIERE | B50: ADRIATICO RESIDENCE | C50: =TRIM(B50) -> ADRIATICO RESIDENCE | D50: via Edmondo De Amicis 39 | E50: GABICCE MARE | F50: =C50&"_"&E50&"_"&D50 -> ADRIATICO RESIDENCE_GABICCE MARE_via Edmondo De Amicis 39 | G50: GABICCE MARE | H50: www.adriaticoresidence.com | I50: info@adriaticoresidence.com
A51: CAMPEGGI | B51: ADRIATICO | C51: =TRIM(B51) -> ADRIATICO | D51: viale Scarfiotti 3 | E51: PORTO RECANATI | F51: =C51&"_"&E51&"_"&D51 -> ADRIATICO_PORTO RECANATI_viale Scarfiotti 3 | G51: PORTO RECANATI | H51: www.campeggioclubadriatico.it | I51: cca@campeggioclubadriatico.it
A52: ALLOGGI IN AFFITTO | B52: AFFITTACAMERE ABELE | C52: =TRIM(B52) -> AFFITTACAMERE ABELE | D52: via Leopardi 84 | E52: PORTO RECANATI | F52: =C52&"_"&E52&"_"&D52 -> AFFITTACAMERE ABELE_PORTO RECANATI_via Leopardi 84 | I52: info@abelecamere.it
A53: ALLOGGI IN AFFITTO | B53: AFFITTACAMERE ACQUA SALATA | C53: =TRIM(B53) -> AFFITTACAMERE ACQUA SALATA | D53: via augusto elia 1 | E53: NUMANA | F53: =C53&"_"&E53&"_"&D53 -> AFFITTACAMERE ACQUA SALATA_NUMANA_via augusto elia 1 | G53: NUMANA | H53: www.affittacamerenumana.it | I53: info@affittacamerenumana.it
A54: ALLOGGI IN AFFITTO | B54: AFFITTACAMERE ACQUARELLO | C54: =TRIM(B54) -> AFFITTACAMERE ACQUARELLO | D54: contrada Acquarello 11 | E54: LAPEDONA | F54: =C54&"_"&E54&"_"&D54 -> AFFITTACAMERE ACQUARELLO_LAPEDONA_contrada Acquarello 11 | G54: LAPEDONA | H54: www.agriturismoacquarello.it | I54: info@agriturismoacquarello.it
A55: ALLOGGI IN AFFITTO | B55: AFFITTACAMERE ALBACHIARA | C55: =TRIM(B55) -> AFFITTACAMERE ALBACHIARA | D55: p.zza f.lli Cervi 13 | E55: OFFIDA | F55: =C55&"_"&E55&"_"&D55 -> AFFITTACAMERE ALBACHIARA_OFFIDA_p.zza f.lli Cervi 13 | H55: www.affittacamerealbachiara.it | I55: affittacamerealbachiara@gmail.com
A56: ALLOGGI IN AFFITTO | B56: AFFITTACAMERE ANGELA'S ROOM | C56: =TRIM(B56) -> AFFITTACAMERE ANGELA'S ROOM | D56: via Milano 4 | E56: NUMANA | F56: =C56&"_"&E56&"_"&D56 -> AFFITTACAMERE ANGELA'S ROOM_NUMANA_via Milano 4 | G56: MARCELLI | H56: www.numanarooms.com | I56: info@numanarooms.com
A57: ALLOGGI IN AFFITTO | B57: AFFITTACAMERE APPENNINO | C57: =TRIM(B57) -> AFFITTACAMERE APPENNINO | D57: via Garibaldi 9 | E57: APECCHIO | F57: =C57&"_"&E57&"_"&D57 -> AFFITTACAMERE APPENNINO_APECCHIO_via Garibaldi 9 | I57: marcellamartinelli17@gmail.com
A58: ALLOGGI IN AFFITTO | B58: AFFITTACAMERE BELLELLI ALBERTO | C58: =TRIM(B58) -> AFFITTACAMERE BELLELLI ALBERTO | D58: via Cristoforo Colombo 6 | E58: NUMANA | F58: =C58&"_"&E58&"_"&D58 -> AFFITTACAMERE BELLELLI ALBERTO_NUMANA_via Cristoforo Colombo 6 | I58: alberto.bellelli@libero.it
A59: ALLOGGI IN AFFITTO | B59: AFFITTACAMERE CASA RELAX | C59: =TRIM(B59) -> AFFITTACAMERE CASA RELAX | D59: via Indipendenza 63/E | E59: CIVITANOVA MARCHE | F59: =C59&"_"&E59&"_"&D59 -> AFFITTACAMERE CASA RELAX_CIVITANOVA MARCHE_via Indipendenza 63/E | G59: CIVITANOVA MARCHE | I59: ciontea@tiscali.it
A60: ALLOGGI IN AFFITTO | B60: AFFITTACAMERE CIVICO 28 | C60: =TRIM(B60) -> AFFITTACAMERE CIVICO 28 | D60: Via Minniti 28 | E60: CUPRA MARITTIMA | F60: =C60&"_"&E60&"_"&D60 -> AFFITTACAMERE CIVICO 28_CUPRA MARITTIMA_Via Minniti 28 | G60: CUPRA MARITTIMA | I60: cupracivico28@gmail.com
A61: ALLOGGI IN AFFITTO | B61: AFFITTACAMERE DA ALDO | C61: =TRIM(B61) -> AFFITTACAMERE DA ALDO | D61: viale Dante Alighieri 104 | E61: FANO | F61: =C61&"_"&E61&"_"&D61 -> AFFITTACAMERE DA ALDO_FANO_viale Dante Alighieri 104 | G61: FANO | I61: aldo@tagliatesta.it
A62: ALLOGGI IN AFFITTO | B62: AFFITTACAMERE DA PATRIZIA | C62: =TRIM(B62) -> AFFITTACAMERE DA PATRIZIA | D62: via Trivio 48 | E62: MONTEGRANARO | F62: =C62&"_"&E62&"_"&D62 -> AFFITTACAMERE DA PATRIZIA_MONTEGRANARO_via Trivio 48 | G62: MONTEGRANARO | I62: c.roselli@odcfermo.it
A63: ALLOGGI IN AFFITTO | B63: AFFITTACAMERE DA SABRI | C63: =TRIM(B63) -> AFFITTACAMERE DA SABRI | D63: VIA RISORGIMENTO 77 | E63: NUMANA | F63: =C63&"_"&E63&"_"&D63 -> AFFITTACAMERE DA SABRI_NUMANA_VIA RISORGIMENTO 77 | G63: NUMANA | I63: sabrinazo@hotmail.com
A64: ALLOGGI IN AFFITTO | B64: AFFITTACAMERE DA TINA | C64: =TRIM(B64) -> AFFITTACAMERE DA TINA | D64: via Roncosanbaccio 71 | E64: FANO | F64: =C64&"_"&E64&"_"&D64 -> AFFITTACAMERE DA TINA_FANO_via Roncosanbaccio 71 | G64: FANO | I64: ennio.and@libero.it
A65: ALLOGGI IN AFFITTO | B65: AFFITTACAMERE DEL VIAGGIATORE | C65: =TRIM(B65) -> AFFITTACAMERE DEL VIAGGIATORE | D65: Via Giordano Bruno 4 | E65: ANCONA | F65: =C65&"_"&E65&"_"&D65 -> AFFITTACAMERE DEL VIAGGIATORE_ANCONA_Via Giordano Bruno 4 | G65: ANCONA | I65: info@affittacameredelviaggiatore.it
A66: ALLOGGI IN AFFITTO | B66: AFFITTACAMERE DOLCI COLLINE | C66: =TRIM(B66) -> AFFITTACAMERE DOLCI COLLINE | D66: via San Lazzaro 124/b | E66: OFFIDA | F66: =C66&"_"&E66&"_"&D66 -> AFFITTACAMERE DOLCI COLLINE_OFFIDA_via San Lazzaro 124/b | I66: paperino124b@alice.it
A67: ALLOGGI IN AFFITTO | B67: AFFITTACAMERE ELIA EMMA | C67: =TRIM(B67) -> AFFITTACAMERE ELIA EMMA | D67: frazione San Martino 27 | E67: ACQUASANTA TERME | F67: =C67&"_"&E67&"_"&D67 -> AFFITTACAMERE ELIA EMMA_ACQUASANTA TERME_frazione San Martino 27 | G67: CASADUNA
A68: ALLOGGI IN AFFITTO | B68: AFFITTACAMERE EURO | C68: =TRIM(B68) -> AFFITTACAMERE EURO | D68: corso giuseppe mazzini 142 | E68: ANCONA | F68: =C68&"_"&E68&"_"&D68 -> AFFITTACAMERE EURO_ANCONA_corso giuseppe mazzini 142 | G68: ANCONA | I68: affittacamereeuro@hotmail.it
A69: ALLOGGI IN AFFITTO | B69: AFFITTACAMERE F.LLI ROSSI | C69: =TRIM(B69) -> AFFITTACAMERE F.LLI ROSSI | D69: via dell'Industria 85 | E69: FILOTTRANO | F69: =C69&"_"&E69&"_"&D69 -> AFFITTACAMERE F.LLI ROSSI_FILOTTRANO_via dell'Industria 85 | G69: filottrano | I69: simonerossi1977@libero.it
A70: ALLOGGI IN AFFITTO | B70: AFFITTACAMERE FORO' LOLITA | C70: =TRIM(B70) -> AFFITTACAMERE FORO' LOLITA | D70: via ugo la malfa 13 | E70: FERMO | F70: =C70&"_"&E70&"_"&D70 -> AFFITTACAMERE FORO' LOLITA_FERMO_via ugo la malfa 13 | G70: FERMO
A71: ALLOGGI IN AFFITTO | B71: AFFITTACAMERE I VICOLI | C71: =TRIM(B71) -> AFFITTACAMERE I VICOLI | D71: via roma 120 | E71: NUMANA | F71: =C71&"_"&E71&"_"&D71 -> AFFITTACAMERE I VICOLI_NUMANA_via roma 120 | G71: NUMANA | H71: www.ivicoli.it | I71: info@ivicoli.it
A72: ALLOGGI IN AFFITTO | B72: AFFITTACAMERE IL GUASCO | C72: =TRIM(B72) -> AFFITTACAMERE IL GUASCO | D72: Via San Pietro 3 | E72: ANCONA | F72: =C72&"_"&E72&"_"&D72 -> AFFITTACAMERE IL GUASCO_ANCONA_Via San Pietro 3 | G72: ANCONA | I72: info@serpilli.com
A73: ALLOGGI IN AFFITTO | B73: AFFITTACAMERE LA LOCOMOTIVA DI PAOLA PETRUCCI | C73: =TRIM(B73) -> AFFITTACAMERE LA LOCOMOTIVA DI PAOLA PETRUCCI | D73: via Don Minzoni 31 | E73: CHIARAVALLE | F73: =C73&"_"&E73&"_"&D73 -> AFFITTACAMERE LA LOCOMOTIVA DI PAOLA PETRUCCI_CHIARAVALLE_via Don Minzoni 31 | H73: www.affittacamerelalocomotiva.it | I73: lalocomotiva01@tiscali.it
A74: ALLOGGI IN AFFITTO | B74: AFFITTACAMERE LA PALOMBA | C74: =TRIM(B74) -> AFFITTACAMERE LA PALOMBA | D74: borgo Gramsci 10 | E74: MONDAVIO | F74: =C74&"_"&E74&"_"&D74 -> AFFITTACAMERE LA PALOMBA_MONDAVIO_borgo Gramsci 10 | G74: MONDAVIO | I74: info@lapalomba.it
A75: ALLOGGI IN AFFITTO | B75: AFFITTACAMERE LA PIAZZETTA 2 | C75: =TRIM(B75) -> AFFITTACAMERE LA PIAZZETTA 2 | D75: Piazzale delle tremiti 5 | E75: NUMANA | F75: =C75&"_"&E75&"_"&D75 -> AFFITTACAMERE LA PIAZZETTA 2_NUMANA_Piazzale delle tremiti 5 | G75: NUMANA | I75: info@camerenumana.it
A76: ALLOGGI IN AFFITTO | B76: AFFITTACAMERE LA PIAZZETTA | C76: =TRIM(B76) -> AFFITTACAMERE LA PIAZZETTA | D76: via Venezia 29 | E76: NUMANA | F76: =C76&"_"&E76&"_"&D76 -> AFFITTACAMERE LA PIAZZETTA_NUMANA_via Venezia 29 | G76: NUMANA
A77: ALLOGGI IN AFFITTO | B77: AFFITTACAMERE LA PIEVE | C77: =TRIM(B77) -> AFFITTACAMERE LA PIEVE | E77: ESANATOGLIA | F77: =C77&"_"&E77&"_"&D77 -> AFFITTACAMERE LA PIEVE_ESANATOGLIA_ | G77: Esanatoglia | I77: info@ristorantegrillcross.it
A78: ALLOGGI IN AFFITTO | B78: AFFITTACAMERE LA STANZA DI FRANCESCA | C78: =TRIM(B78) -> AFFITTACAMERE LA STANZA DI FRANCESCA | D78: Via A. Tiraboschi 5/A | E78: ANCONA | F78: =C78&"_"&E78&"_"&D78 -> AFFITTACAMERE LA STANZA DI FRANCESCA_ANCONA_Via A. Tiraboschi 5/A | G78: ANCONA | I78: depalmacasa@gmail.com
A79: ALLOGGI IN AFFITTO | B79: AFFITTACAMERE LATINI LUCIA | C79: =TRIM(B79) -> AFFITTACAMERE LATINI LUCIA | D79: localita' civita 43 | E79: FABRIANO | F79: =C79&"_"&E79&"_"&D79 -> AFFITTACAMERE LATINI LUCIA_FABRIANO_localita' civita 43 | G79: FABRIANO | H79: www.villagioiacivita.it | I79: info@villagioiacivita.it
A80: ALLOGGI IN AFFITTO | B80: AFFITTACAMERE LE MAGNOLIE | C80: =TRIM(B80) -> AFFITTACAMERE LE MAGNOLIE | D80: Via Ussita 12 | E80: MONTEMARCIANO | F80: =C80&"_"&E80&"_"&D80 -> AFFITTACAMERE LE MAGNOLIE_MONTEMARCIANO_Via Ussita 12 | G80: MONTEMARCIANO | I80: supercristian79@gmail.com
A81: ALLOGGI IN AFFITTO | B81: AFFITTACAMERE LE TRE SORELLE | C81: =TRIM(B81) -> AFFITTACAMERE LE TRE SORELLE | D81: via Grilli 4 | E81: SIROLO | F81: =C81&"_"&E81&"_"&D81 -> AFFITTACAMERE LE TRE SORELLE_SIROLO_via Grilli 4 | I81: info@affittacamereletresorelle.it
A82: ALLOGGI IN AFFITTO | B82: AFFITTACAMERE LEOPARDI 59 | C82: =TRIM(B82) -> AFFITTACAMERE LEOPARDI 59 | D82: G. Leopardi 59 | E82: CAMERINO | F82: =C82&"_"&E82&"_"&D82 -> AFFITTACAMERE LEOPARDI 59_CAMERINO_G. Leopardi 59 | I82: amministrazone@6tour.com
A83: ALLOGGI IN AFFITTO | B83: AFFITTACAMERE LUCONI | C83: =TRIM(B83) -> AFFITTACAMERE LUCONI | D83: VIA PANTIERE 1 | E83: JESI | F83: =C83&"_"&E83&"_"&D83 -> AFFITTACAMERE LUCONI_JESI_VIA PANTIERE 1 | G83: JESI | I83: info@affittacamereluconi.it
A84: ALLOGGI IN AFFITTO | B84: AFFITTACAMERE MARZIALI GIANLUCA | C84: =TRIM(B84) -> AFFITTACAMERE MARZIALI GIANLUCA | D84: contrada Marulla 2 | E84: MONTEFALCONE APPENNINO | F84: =C84&"_"&E84&"_"&D84 -> AFFITTACAMERE MARZIALI GIANLUCA_MONTEFALCONE APPENNINO_contrada Marulla 2 | I84: gianluca.marziali@coldiretti.it
A85: ALLOGGI IN AFFITTO | B85: AFFITTACAMERE MORELLI | C85: =TRIM(B85) -> AFFITTACAMERE MORELLI | D85: via Flaminia 5 | E85: NUMANA | F85: =C85&"_"&E85&"_"&D85 -> AFFITTACAMERE MORELLI_NUMANA_via Flaminia 5 | G85: NUMANA | H85: Www.morellicamerenumana.it | I85: Info@morellicamerenumana.it
A86: ALLOGGI IN AFFITTO | B86: AFFITTACAMERE OASI | C86: =TRIM(B86) -> AFFITTACAMERE OASI | D86: via belsito 17 | E86: FANO | F86: =C86&"_"&E86&"_"&D86 -> AFFITTACAMERE OASI_FANO_via belsito 17 | G86: FANO | I86: hotel.oasi@gostec.net
A87: ALLOGGI IN AFFITTO | B87: AFFITTACAMERE OASI | C87: =TRIM(B87) -> AFFITTACAMERE OASI | D87: via belsito 19 | E87: FANO | F87: =C87&"_"&E87&"_"&D87 -> AFFITTACAMERE OASI_FANO_via belsito 19 | G87: TORRETTE | I87: hotel.oasi@gostec.net
A88: ALLOGGI IN AFFITTO | B88: AFFITTACAMERE PAVONI | C88: =TRIM(B88) -> AFFITTACAMERE PAVONI | D88: via ancona 66 | E88: OSIMO | F88: =C88&"_"&E88&"_"&D88 -> AFFITTACAMERE PAVONI_OSIMO_via ancona 66 | G88: OSIMO | I88: marcopav@email.com
A89: ALLOGGI IN AFFITTO | B89: AFFITTACAMERE PEPITO IN CITTA' | C89: =TRIM(B89) -> AFFITTACAMERE PEPITO IN CITTA' | D89: Via G. Mazzini 2 | E89: JESI | F89: =C89&"_"&E89&"_"&D89 -> AFFITTACAMERE PEPITO IN CITTA'_JESI_Via G. Mazzini 2 | G89: JESI | I89: willyvigna@gmail.com
A90: ALLOGGI IN AFFITTO | B90: AFFITTACAMERE PEPPINE' | C90: =TRIM(B90) -> AFFITTACAMERE PEPPINE' | E90: MONTEFORTINO | F90: =C90&"_"&E90&"_"&D90 -> AFFITTACAMERE PEPPINE'_MONTEFORTINO_ | I90: virgilio.siquilini@gmail.com
A91: ALLOGGI IN AFFITTO | B91: AFFITTACAMERE PETTINELLI | C91: =TRIM(B91) -> AFFITTACAMERE PETTINELLI | D91: Via Merolli 10 | E91: SASSOFERRATO | F91: =C91&"_"&E91&"_"&D91 -> AFFITTACAMERE PETTINELLI_SASSOFERRATO_Via Merolli 10 | G91: SASSOFERRATO
A92: ALLOGGI IN AFFITTO | B92: AFFITTACAMERE RESIDENCE LE PALME | C92: =TRIM(B92) -> AFFITTACAMERE RESIDENCE LE PALME | D92: Via Amalfi SNC | E92: NUMANA | F92: =C92&"_"&E92&"_"&D92 -> AFFITTACAMERE RESIDENCE LE PALME_NUMANA_Via Amalfi SNC | G92: NUMANA | I92: info@residencelepalme.com
A93: ALLOGGI IN AFFITTO | B93: AFFITTACAMERE SAN GIORGIO | C93: =TRIM(B93) -> AFFITTACAMERE SAN GIORGIO | D93: via XX Settembre 196 | E93: PORTO SAN GIORGIO | F93: =C93&"_"&E93&"_"&D93 -> AFFITTACAMERE SAN GIORGIO_PORTO SAN GIORGIO_via XX Settembre 196 | G93: PORTO SAN GIORGIO | I93: pensione.san.giorgio@hotmail.it
A94: ALLOGGI IN AFFITTO | B94: AFFITTACAMERE SERINI CARMELA | C94: =TRIM(B94) -> AFFITTACAMERE SERINI CARMELA | D94: via M.Armanno, via C.Augusto 10, 9 | E94: PIORACO | F94: =C94&"_"&E94&"_"&D94 -> AFFITTACAMERE SERINI CARMELA_PIORACO_via M.Armanno, via C.Augusto 10, 9 | I94: c.ilari@macerata.confartigianato.it
A95: ALLOGGI IN AFFITTO | B95: AFFITTACAMERE SIMONETTI | C95: =TRIM(B95) -> AFFITTACAMERE SIMONETTI | D95: piazza francesco basili 4 | E95: LORETO | F95: =C95&"_"&E95&"_"&D95 -> AFFITTACAMERE SIMONETTI_LORETO_piazza francesco basili 4 | G95: LORETO | H95: www.dormialoreto.it | I95: contact@affittacameresimonetti.it
A96: ALLOGGI IN AFFITTO | B96: AFFITTACAMERE SIROLO | C96: =TRIM(B96) -> AFFITTACAMERE SIROLO | D96: Via Galilei 6 | E96: ANCONA | F96: =C96&"_"&E96&"_"&D96 -> AFFITTACAMERE SIROLO_ANCONA_Via Galilei 6 | G96: ANCONA | I96: affittacamere.sirolo@gmail.com
A97: ALLOGGI IN AFFITTO | B97: AFFITTACAMERE TIEPOLO 4 | C97: =TRIM(B97) -> AFFITTACAMERE TIEPOLO 4 | D97: TIEPOLO 4 | E97: CAMERINO | F97: =C97&"_"&E97&"_"&D97 -> AFFITTACAMERE TIEPOLO 4_CAMERINO_TIEPOLO 4 | G97: CAMERINO | I97: amministrazione@6tour.com
A98: ALLOGGI IN AFFITTO | B98: AFFITTACAMERE TORRESI | C98: =TRIM(B98) -> AFFITTACAMERE TORRESI | D98: via Galilei 6 | E98: ANCONA | F98: =C98&"_"&E98&"_"&D98 -> AFFITTACAMERE TORRESI_ANCONA_via Galilei 6 | I98: affittacamere.torresi@gmail.com
A99: ALLOGGI IN AFFITTO | B99: AFFITTACAMERE TORRETTE DI ANCONA | C99: =TRIM(B99) -> AFFITTACAMERE TORRETTE DI ANCONA | D99: via Conca 14 | E99: ANCONA | F99: =C99&"_"&E99&"_"&D99 -> AFFITTACAMERE TORRETTE DI ANCONA_ANCONA_via Conca 14 | G99: Torrette di Ancona | I99: giannicesarone@gmail.com
A100: ALLOGGI IN AFFITTO | B100: AFFITTACAMERE TRABALLONI FEDERICA | C100: =TRIM(B100) -> AFFITTACAMERE TRABALLONI FEDERICA | D100: borgo san giovanni 33 | E100: ESANATOGLIA | F100: =C100&"_"&E100&"_"&D100 -> AFFITTACAMERE TRABALLONI FEDERICA_ESANATOGLIA_borgo san giovanni 33 | G100: ESANATOGLIA | I100: debby.brugnolaòlibero.it
...

Sheet RICERCA
B1: RICERCA STRUTTURA
B3: NOME STRUTTURA | C3: 124 AFFITTACAMERE_TOLENTINO_via Sandro Pertini 55 | D3: ho inserito la chiave perché ci sono diverse strutture con lo stesso nome in città diverse
B4: CITTA' | C4: =_xlfn.XLOOKUP(C3,'Strutture ricettive'!F:F,'Strutture ricettive'!E:E) -> TOLENTINO
B5: INDIRIZZO | C5: =IF(_xlfn.XLOOKUP($C$3,'Strutture ricettive'!F:F,'Strutture ricettive'!D:D)="","Non disponibile",_xlfn.XLOOKUP($C$3,'Strutture ricettive'!F:F,'Strutture ricettive'!D:D)) -> via Sandro Pertini 55
B6: EMAIL | C6: =IF(_xlfn.XLOOKUP($C$3,'Strutture ricettive'!F:F,'Strutture ricettive'!I:I)="","Non disponibile",_xlfn.XLOOKUP($C$3,'Strutture ricettive'!F:F,'Strutture ricettive'!I:I)) -> info@124tolentino.it.
B7: INDIRIZZO WEB | C7: =IF(_xlfn.XLOOKUP($C$3,'Strutture ricettive'!F:F,'Strutture ricettive'!H:H)="","Non disponibile",_xlfn.XLOOKUP($C$3,'Strutture ricettive'!F:F,'Strutture ricettive'!H:H)) -> Non disponibile
B8: Numero totale strutture | C8: =COUNTA('Strutture ricettive'!B:B) -> 6253
B9: Numero strutture per LOCALITA' | C9: =COUNTIF('Strutture ricettive'!E:E,C4) -> 37

Sheet PIVOT
A1: Città | B1: (Tutto)
A3: Categoria | B3: Numero strutture
A4: ALBERGHI | B4: 814
A5: ALLOGGI AGRITURISTICI | B5: 829
A6: ALLOGGI IN AFFITTO | B6: 540
A7: ALTRI ALLOGGI PRIVATI | B7: 719
A8: ALTRI ESERCIZI RICETTIVI | B8: 13
A9: AREE DI SOSTA (PLEIN AIR) | B9: 86
A10: BED & BREAKFAST | B10: 1808
A11: CAMPEGGI | B11: 93
A12: CASE PER FERIE | B12: 82
A13: OSTELLI PER LA GIOVENTU' | B13: 30
A14: RESIDENZE TURISTICO ALBERGHIERE | B14: 52
A15: RIFUGI | B15: 16
... A18: VILLAGGI TURISTICI | B18: 17
A19: (vuoto)
A20: Totale complessivo | B20: 6252
